{
    "Q": {
        "damage": {
            "type": "phys",
            "system": "evolveMinMax",
            "minDmg": [
                45, 61.25, 77.5, 93.75, 110
            ],
            "maxDmg": [
                101.25, 137.8125, 174.375, 210.9375, 247.5
            ],
            "evolveMaxDmg": [
                168.75, 229.6875, 290.625, 351.5625, 412.5
            ],
            "minBonusADRatio": 0.4,
            "maxBonusADRatio": 0.9,
            "evolveMaxBonusADRatio": 1.5,
            "minAPRatio": 0.25,
            "maxAPRatio": 0.5625,
            "evolveMaxAPRatio": 0.9375
        },
        "coolDown": [
            8, 7.5, 7, 6.5, 6
        ]
    },
    "W": {
        "damage": {
            "type": "magic",
            "system": "single",
            "dmg": [
                30, 55, 80, 105, 130
            ],
            "ADRatio": 1.3,
            "APRatio": 0.7
        },
        "coolDown": [
            22, 20, 18, 16, 14
        ],
        "evolveCoolDownRatioRefundOnHit": 0.7
    },
    "E": {
        "bonusAttackSpeed": {
            "duration": 4,
            "attackSpeed": [
                0.40, 0.45, 0.50, 0.55, 0.60
            ]
        },
        "coolDown": [
            16,15,14,13,12
        ],
        "coolDownRefundOnAuto": 0.5
    },
    "R": {
        "shield": {
            "duration": 2,
            "type": "all",
            "targets": "Self",
            "shield": [
                75, 100, 125
            ],
            "ADRatio": [
                1, 1.5, 2
            ],
            "APRatio": 0.75
        },
        "coolDown": [
            110, 90, 70
        ]
    },
    "passive": {
        "onHitPermanent": {
            "damage": {
                "dmgByLvl": [
                    4, 4, 5, 5, 5, 6, 6, 6, 7,
                    7, 8, 8, 8, 9, 9, 9, 10, 10
                ],
                "dmgPerStackByLvl": [
                    1, 1, 1, 2, 2, 2, 2, 3, 3,
                     3, 3, 4, 4, 4, 4, 5, 5, 5
                ],
                "APRatioByStack": [
                    0.1, 0.125, 0.15, 0.175, 0.2
                ]
            }
        },
        "autoEmpower": {
            "damage": {
                "type":"magic",
                "enemyMissingHPRatio": 0.15,
                "enemyMissingHPRatioPer100AP": 0.025
            },
            "autoCoolDown": 5
        }
    },
    "stats": {
        "baseHP": 600,
        "hpPerLevel": 88,
        "baseHPRegen": 3.5,
        "hpRegenPerLevel": 0.55,
        "mana": {
            "base": 344.88,
            "manaPerLevel": 38,
            "manaBaseRegen": 8.2,
            "manaRegenPerLevel": 0.45
        },
        "baseDamage": 59,
        "damagePerLevel": 1.7,
        "baseArmor": 28,
        "armorPerLevel": 3,
        "baseMagicResist": 30,
        "magicResistPerLevel": 0.5,
        "attackSpeed": 0.644,
        "attackSpeedRatio": 0.644,
        "attackSpeedPerLevel": 0.018
    }
}